<annotation>
	<folder>JPEGImages</folder>
	<filename>05b25ac6a4bd1ea908f113676d206341.jpg</filename>
	<path>C:\Users\User\Workspace\Dataset\dataset-julien\JPEGImages\05b25ac6a4bd1ea908f113676d206341.jpg</path>
	<source>
		<database>Unknown</database>
	</source>
	<size>
		<width>976</width>
		<height>549</height>
		<depth>3</depth>
	</size>
	<segmented>0</segmented>
	<object>
		<name>with_mask</name>
		<pose>Unspecified</pose>
		<truncated>0</truncated>
		<difficult>0</difficult>
		<bndbox>
			<xmin>171</xmin>
			<ymin>106</ymin>
			<xmax>405</xmax>
			<ymax>405</ymax>
		</bndbox>
	</object>
</annotation>
