<annotation>
	<folder>JPEGImages</folder>
	<filename>177cd8213775da3a8ea5785f72f79a56.jpg</filename>
	<path>C:\Users\youss\Pictures\Screenshots\covid_mask\jpeg_img\JPEGImages\177cd8213775da3a8ea5785f72f79a56.jpg</path>
	<source>
		<database>Unknown</database>
	</source>
	<size>
		<width>1306</width>
		<height>900</height>
		<depth>3</depth>
	</size>
	<segmented>0</segmented>
	<object>
		<name>with_mask</name>
		<pose>Unspecified</pose>
		<truncated>0</truncated>
		<difficult>0</difficult>
		<bndbox>
			<xmin>724</xmin>
			<ymin>129</ymin>
			<xmax>868</xmax>
			<ymax>314</ymax>
		</bndbox>
	</object>
	<object>
		<name>with_incorrect_mask</name>
		<pose>Unspecified</pose>
		<truncated>0</truncated>
		<difficult>0</difficult>
		<bndbox>
			<xmin>349</xmin>
			<ymin>268</ymin>
			<xmax>535</xmax>
			<ymax>425</ymax>
		</bndbox>
	</object>
</annotation>
