<annotation>
	<folder>lulu</folder>
	<filename>276389918a4a11837d3f60c30ee874b3.jpg</filename>
	<path>C:\Users\lucie\Documents\GitHub\detection_masques\images_recherche\all\lulu\276389918a4a11837d3f60c30ee874b3.jpg</path>
	<source>
		<database>Unknown</database>
	</source>
	<size>
		<width>1200</width>
		<height>799</height>
		<depth>3</depth>
	</size>
	<segmented>0</segmented>
	<object>
		<name>with_mask</name>
		<pose>Unspecified</pose>
		<truncated>0</truncated>
		<difficult>0</difficult>
		<bndbox>
			<xmin>688</xmin>
			<ymin>340</ymin>
			<xmax>805</xmax>
			<ymax>491</ymax>
		</bndbox>
	</object>
	<object>
		<name>with_incorrect_mask</name>
		<pose>Unspecified</pose>
		<truncated>0</truncated>
		<difficult>0</difficult>
		<bndbox>
			<xmin>512</xmin>
			<ymin>152</ymin>
			<xmax>620</xmax>
			<ymax>330</ymax>
		</bndbox>
	</object>
</annotation>
