<?xml version="1.0"?>
<annotation>
<folder>data</folder>
<filename>6330eaa41c0b9f8e7a2cccccb3442136.jpg</filename>
<path/>
<source>
<database>Unknown</database>
</source>
<size>
<width>2222</width>
<height>1667</height>
<depth>3</depth>
</size>
<segmented>0</segmented>
<object>
<name>with_incorrect_mask</name>
<pose>Unspecified</pose>
<truncated>0</truncated>
<occluded>0</occluded>
<difficult>0</difficult>
<bndbox>
<xmin>740</xmin>
<ymin>174</ymin>
<xmax>1343</xmax>
<ymax>1116</ymax>
</bndbox>
</object>
</annotation>