<annotation>
	<folder>JPEGImages</folder>
	<filename>807e7a706250829e823c07ce461a9cf3.jpg</filename>
	<path>C:\Users\User\Workspace\Dataset\dataset-julien\JPEGImages\807e7a706250829e823c07ce461a9cf3.jpg</path>
	<source>
		<database>Unknown</database>
	</source>
	<size>
		<width>445</width>
		<height>445</height>
		<depth>3</depth>
	</size>
	<segmented>0</segmented>
	<object>
		<name>with_mask</name>
		<pose>Unspecified</pose>
		<truncated>0</truncated>
		<difficult>0</difficult>
		<bndbox>
			<xmin>156</xmin>
			<ymin>80</ymin>
			<xmax>293</xmax>
			<ymax>284</ymax>
		</bndbox>
	</object>
</annotation>
