<annotation>
	<folder>JPEGImages</folder>
	<filename>8ad510459aa8244ce7700a2adedc1f72.jpg</filename>
	<path>D:\ESIREM\ESIREM-sem9\sys_int\brouce\projet\face-mask-dataset-ilc-2021\JPEGImages\8ad510459aa8244ce7700a2adedc1f72.jpg</path>
	<source>
		<database>Unknown</database>
	</source>
	<size>
		<width>1024</width>
		<height>683</height>
		<depth>3</depth>
	</size>
	<segmented>0</segmented>
	<object>
		<name>without_mask</name>
		<pose>Unspecified</pose>
		<truncated>0</truncated>
		<difficult>0</difficult>
		<bndbox>
			<xmin>142</xmin>
			<ymin>220</ymin>
			<xmax>226</xmax>
			<ymax>303</ymax>
		</bndbox>
	</object>
	<object>
		<name>without_mask</name>
		<pose>Unspecified</pose>
		<truncated>0</truncated>
		<difficult>0</difficult>
		<bndbox>
			<xmin>750</xmin>
			<ymin>64</ymin>
			<xmax>800</xmax>
			<ymax>128</ymax>
		</bndbox>
	</object>
	<object>
		<name>with_mask</name>
		<pose>Unspecified</pose>
		<truncated>0</truncated>
		<difficult>0</difficult>
		<bndbox>
			<xmin>544</xmin>
			<ymin>119</ymin>
			<xmax>619</xmax>
			<ymax>198</ymax>
		</bndbox>
	</object>
</annotation>
