<?xml version="1.0"?>
<annotation>
<folder>data</folder>
<filename>ddfa85b991595f133f65f445c01990d7-crop-0.jpg</filename>
<path/>
<source>
<database>Unknown</database>
</source>
<size>
<width>157</width>
<height>214</height>
<depth>3</depth>
</size>
<segmented>0</segmented>
<object>
<name>with_mask</name>
<pose>Unspecified</pose>
<truncated>0</truncated>
<occluded>0</occluded>
<difficult>0</difficult>
<bndbox>
<xmin>56</xmin>
<ymin>18</ymin>
<xmax>95</xmax>
<ymax>66</ymax>
</bndbox>
</object>
</annotation>